gbrokerexe/__init__.py
gbrokerexe/oanda.py
gbrokerexe/py.typed
gbrokerexe-0.1.7.dist-info/LICENSE
gbrokerexe-0.1.7.dist-info/WHEEL
gbrokerexe-0.1.7.dist-info/METADATA
gbrokerexe-0.1.7.dist-info/RECORD
