Metadata-Version: 2.1
Name: gbrokerexe
Version: 0.1.7
Summary: Generic Python Package for Brokerage and Trade Executions.
Home-page: https://github.com/altcp/gbrokerexe
License: GNU GPL v3.0
Author: altcp
Author-email: colab.tcp@gmail.com
Requires-Python: >=3.8,<3.11
Classifier: License :: Other/Proprietary License
Classifier: Programming Language :: Python :: 3
Classifier: Programming Language :: Python :: 3.8
Classifier: Programming Language :: Python :: 3.9
Requires-Dist: numpy (==1.19.5)
Requires-Dist: pandas (>=1.3.2,<2.0.0)
Requires-Dist: pytest (>=6.2.4,<7.0.0)
Project-URL: Repository, https://github.com/altcp/gbrokerexe
